pymonom/notification/__init__.py
pymonom/notification/notification.py
pymonom-0.0.1.dist-info/WHEEL
pymonom-0.0.1.dist-info/METADATA
pymonom-0.0.1.dist-info/RECORD
